LICENSE
README.md
setup.py
GO_3_data_model.egg-info/PKG-INFO
GO_3_data_model.egg-info/SOURCES.txt
GO_3_data_model.egg-info/dependency_links.txt
GO_3_data_model.egg-info/requires.txt
GO_3_data_model.egg-info/top_level.txt
datamodel/__init__.py
datamodel/base.py
datamodel/create.py
datamodel/input/__data.py
datamodel/input/__init__.py
datamodel/input/__reliability.py
datamodel/input/__sections.py
datamodel/input/__static.py
datamodel/input/__staticinner.py
datamodel/input/__timeseries.py
datamodel/input/data.py
datamodel/input/database.py
datamodel/input/reliability.py
datamodel/input/reliabilitybase.py
datamodel/input/sections.py
datamodel/input/sectionsbase.py
datamodel/input/static.py
datamodel/input/staticbase.py
datamodel/input/staticinner.py
datamodel/input/staticinnerbase.py
datamodel/input/timeseries.py
datamodel/input/timeseriesbase.py
datamodel/output/__data.py
datamodel/output/__init__.py
datamodel/output/__sections.py
datamodel/output/__timeseries.py
datamodel/output/data.py
datamodel/output/database.py
datamodel/output/sections.py
datamodel/output/sectionsbase.py
datamodel/output/timeseries.py
datamodel/output/timeseriesbase.py