Metadata-Version: 2.1
Name: GO-3-data-model
Version: 1.0.2
Summary: Repository for model formulation of Grid Optimization Competition #3
Author: NREL
License: UNKNOWN
Platform: UNKNOWN
License-File: LICENSE
